[{"cubeType":2,"time":0.0,"x":0.08,"y":9.1,"z":8.0},{"cubeType":3,"time":0.0,"x":-0.08,"y":9.1,"z":8.0},{"cubeType":0,"time":0.48,"x":0.1,"y":9.14,"z":8.0},{"cubeType":1,"time":0.48,"x":-0.1,"y":9.14,"z":8.0},{"cubeType":3,"time":0.96,"x":-0.08,"y":9.1,"z":8.0},{"cubeType":2,"time":1.43999994,"x":0.08,"y":9.1,"z":8.0},{"cubeType":1,"time":1.92,"x":-0.08,"y":9.12,"z":8.0},{"cubeType":0,"time":2.39999986,"x":0.08,"y":9.12,"z":8.0},{"cubeType":5,"time":2.87999988,"x":-0.1,"y":9.14,"z":8.0},{"cubeType":2,"time":3.36,"x":0.1,"y":9.14,"z":8.0},{"cubeType":1,"time":3.84,"x":-0.06,"y":9.12,"z":8.0},{"cubeType":0,"time":4.31999969,"x":0.06,"y":9.12,"z":8.0},{"cubeType":5,"time":4.79999971,"x":-0.1,"y":9.2,"z":8.0},{"cubeType":2,"time":5.27999973,"x":0.1,"y":9.2,"z":8.0},{"cubeType":1,"time":5.75999975,"x":-0.06,"y":9.12,"z":8.0},{"cubeType":0,"time":6.24,"x":0.06,"y":9.12,"z":8.0},{"cubeType":2,"time":6.72,"x":0.08,"y":9.12,"z":8.0},{"cubeType":3,"time":6.72,"x":-0.08,"y":9.12,"z":8.0},{"cubeType":1,"time":7.2,"x":-0.06,"y":9.12,"z":8.0},{"cubeType":0,"time":7.68,"x":0.04,"y":9.12,"z":8.0},{"cubeType":3,"time":8.16,"x":-0.04,"y":9.16,"z":8.0},{"cubeType":2,"time":8.639999,"x":0.04,"y":9.16,"z":8.0},{"cubeType":1,"time":9.12,"x":-0.04,"y":9.12,"z":8.0},{"cubeType":3,"time":9.599999,"x":-0.04,"y":9.12,"z":8.0},{"cubeType":6,"time":10.08,"x":0.06,"y":9.2,"z":8.0},{"cubeType":1,"time":10.5599995,"x":-0.04,"y":9.2,"z":8.0},{"cubeType":0,"time":11.04,"x":0.04,"y":9.16,"z":8.0},{"cubeType":2,"time":11.5199995,"x":0.04,"y":9.16,"z":8.0},{"cubeType":5,"time":12.0,"x":-0.06,"y":9.2,"z":8.0},{"cubeType":0,"time":12.48,"x":0.08,"y":9.1,"z":8.0},{"cubeType":1,"time":12.48,"x":-0.08,"y":9.1,"z":8.0},{"cubeType":3,"time":12.96,"x":-0.04,"y":9.12,"z":8.0},{"cubeType":2,"time":13.44,"x":0.04,"y":9.12,"z":8.0},{"cubeType":1,"time":13.92,"x":-0.04,"y":9.14,"z":8.0},{"cubeType":0,"time":14.4,"x":0.04,"y":9.14,"z":8.0},{"cubeType":2,"time":14.88,"x":0.08,"y":9.2,"z":8.0},{"cubeType":3,"time":14.88,"x":-0.08,"y":9.2,"z":8.0},{"cubeType":0,"time":15.36,"x":0.08,"y":9.1,"z":8.0},{"cubeType":1,"time":15.36,"x":-0.08,"y":9.1,"z":8.0},{"cubeType":3,"time":16.32,"x":-0.08,"y":9.22,"z":8.0},{"cubeType":2,"time":16.8,"x":0.08,"y":9.22,"z":8.0},{"cubeType":0,"time":17.2799988,"x":0.08,"y":9.1,"z":8.0},{"cubeType":5,"time":17.76,"x":-0.08,"y":9.24,"z":8.0},{"cubeType":2,"time":18.48,"x":0.08,"y":9.2,"z":8.0},{"cubeType":1,"time":18.96,"x":-0.08,"y":9.1,"z":8.0},{"cubeType":3,"time":19.4399986,"x":-0.1,"y":9.2,"z":8.0},{"cubeType":0,"time":20.4,"x":0.08,"y":9.1,"z":8.0},{"cubeType":1,"time":20.88,"x":-0.08,"y":9.1,"z":8.0},{"cubeType":2,"time":21.3599987,"x":0.08,"y":9.2,"z":8.0},{"cubeType":3,"time":21.84,"x":-0.08,"y":9.2,"z":8.0},{"cubeType":0,"time":22.32,"x":0.08,"y":9.14,"z":8.0},{"cubeType":1,"time":22.32,"x":-0.08,"y":9.14,"z":8.0},{"cubeType":2,"time":22.8,"x":0.08,"y":9.2,"z":8.0},{"cubeType":3,"time":22.8,"x":-0.08,"y":9.2,"z":8.0},{"cubeType":0,"time":23.2799988,"x":0.08,"y":9.14,"z":8.0},{"cubeType":1,"time":23.2799988,"x":-0.08,"y":9.14,"z":8.0},{"cubeType":5,"time":24.24,"x":-0.06,"y":9.24,"z":8.0},{"cubeType":6,"time":24.72,"x":0.06,"y":9.24,"z":8.0},{"cubeType":1,"time":25.1999989,"x":-0.04,"y":9.1,"z":8.0},{"cubeType":0,"time":25.68,"x":0.04,"y":9.1,"z":8.0},{"cubeType":3,"time":26.16,"x":-0.04,"y":9.2,"z":8.0},{"cubeType":2,"time":26.64,"x":0.08,"y":9.2,"z":8.0},{"cubeType":0,"time":27.1199989,"x":0.08,"y":9.16,"z":8.0},{"cubeType":1,"time":27.5999985,"x":-0.04,"y":9.16,"z":8.0},{"cubeType":2,"time":28.08,"x":0.04,"y":9.2,"z":8.0},{"cubeType":5,"time":28.56,"x":-0.06,"y":9.24,"z":8.0},{"cubeType":0,"time":29.039999,"x":0.04,"y":9.12,"z":8.0},{"cubeType":1,"time":29.5199986,"x":-0.08,"y":9.12,"z":8.0},{"cubeType":3,"time":30.0,"x":-0.08,"y":9.2,"z":8.0},{"cubeType":2,"time":30.48,"x":0.04,"y":9.2,"z":8.0},{"cubeType":0,"time":30.96,"x":0.08,"y":9.16,"z":8.0},{"cubeType":1,"time":30.96,"x":-0.08,"y":9.16,"z":8.0},{"cubeType":2,"time":31.92,"x":0.08,"y":9.22,"z":8.0},{"cubeType":3,"time":31.92,"x":-0.08,"y":9.22,"z":8.0},{"cubeType":1,"time":32.3999977,"x":-0.04,"y":9.1,"z":8.0},{"cubeType":0,"time":32.88,"x":0.04,"y":9.1,"z":8.0},{"cubeType":5,"time":33.36,"x":-0.06,"y":9.24,"z":8.0},{"cubeType":2,"time":34.079998,"x":0.04,"y":9.2,"z":8.0},{"cubeType":1,"time":34.5599976,"x":-0.04,"y":9.1,"z":8.0},{"cubeType":3,"time":35.04,"x":-0.1,"y":9.2,"z":8.0},{"cubeType":0,"time":35.52,"x":0.04,"y":9.14,"z":8.0},{"cubeType":1,"time":36.0,"x":-0.04,"y":9.14,"z":8.0},{"cubeType":2,"time":36.48,"x":0.1,"y":9.22,"z":8.0},{"cubeType":0,"time":36.96,"x":0.08,"y":9.14,"z":8.0},{"cubeType":3,"time":37.44,"x":-0.08,"y":9.2,"z":8.0},{"cubeType":2,"time":37.92,"x":0.08,"y":9.2,"z":8.0},{"cubeType":0,"time":38.3999977,"x":0.08,"y":9.14,"z":8.0},{"cubeType":1,"time":38.3999977,"x":-0.08,"y":9.1,"z":8.0},{"cubeType":2,"time":39.12,"x":0.08,"y":9.14,"z":8.0},{"cubeType":3,"time":39.12,"x":-0.08,"y":9.14,"z":8.0},{"cubeType":1,"time":39.84,"x":-0.04,"y":9.1,"z":8.0},{"cubeType":0,"time":40.32,"x":0.04,"y":9.14,"z":8.0},{"cubeType":2,"time":40.5599976,"x":0.08,"y":9.2,"z":8.0},{"cubeType":3,"time":40.5599976,"x":-0.08,"y":9.2,"z":8.0},{"cubeType":1,"time":41.28,"x":-0.08,"y":9.14,"z":8.0},{"cubeType":0,"time":41.76,"x":0.04,"y":9.14,"z":8.0},{"cubeType":2,"time":42.2399979,"x":0.08,"y":9.18,"z":8.0},{"cubeType":3,"time":42.2399979,"x":-0.08,"y":9.18,"z":8.0},{"cubeType":1,"time":42.96,"x":-0.1,"y":9.14,"z":8.0},{"cubeType":0,"time":43.44,"x":0.04,"y":9.12,"z":8.0},{"cubeType":2,"time":43.92,"x":0.08,"y":9.2,"z":8.0},{"cubeType":3,"time":43.92,"x":-0.08,"y":9.2,"z":8.0},{"cubeType":1,"time":44.8799973,"x":-0.04,"y":9.12,"z":8.0},{"cubeType":0,"time":45.36,"x":0.04,"y":9.12,"z":8.0},{"cubeType":2,"time":45.84,"x":0.08,"y":9.2,"z":8.0},{"cubeType":3,"time":45.84,"x":-0.08,"y":9.2,"z":8.0},{"cubeType":0,"time":47.0399971,"x":0.08,"y":9.24,"z":8.0},{"cubeType":1,"time":47.0399971,"x":-0.08,"y":9.24,"z":8.0},{"cubeType":5,"time":47.76,"x":-0.06,"y":9.2,"z":8.0},{"cubeType":6,"time":48.0,"x":0.06,"y":9.2,"z":8.0},{"cubeType":1,"time":48.48,"x":-0.04,"y":9.1,"z":8.0},{"cubeType":0,"time":48.96,"x":0.04,"y":9.1,"z":8.0},{"cubeType":2,"time":49.2,"x":0.1,"y":9.16,"z":8.0},{"cubeType":3,"time":49.2,"x":-0.1,"y":9.16,"z":8.0},{"cubeType":1,"time":50.3999977,"x":-0.04,"y":9.12,"z":8.0},{"cubeType":0,"time":50.8799973,"x":0.04,"y":9.12,"z":8.0},{"cubeType":2,"time":51.12,"x":0.08,"y":9.18,"z":8.0},{"cubeType":3,"time":51.12,"x":-0.08,"y":9.18,"z":8.0},{"cubeType":5,"time":51.6,"x":-0.06,"y":9.2,"z":8.0},{"cubeType":0,"time":52.32,"x":0.08,"y":9.14,"z":8.0},{"cubeType":1,"time":52.32,"x":-0.08,"y":9.14,"z":8.0},{"cubeType":2,"time":54.7199974,"x":0.08,"y":9.2,"z":8.0},{"cubeType":3,"time":54.7199974,"x":-0.08,"y":9.2,"z":8.0},{"cubeType":1,"time":55.1999969,"x":-0.04,"y":9.12,"z":8.0},{"cubeType":0,"time":55.68,"x":0.04,"y":9.12,"z":8.0},{"cubeType":3,"time":56.3999977,"x":-0.04,"y":9.16,"z":8.0},{"cubeType":6,"time":56.8799973,"x":0.06,"y":9.2,"z":8.0},{"cubeType":1,"time":57.6,"x":-0.04,"y":9.1,"z":8.0},{"cubeType":3,"time":58.079998,"x":-0.1,"y":9.18,"z":8.0},{"cubeType":0,"time":58.5599976,"x":0.04,"y":9.1,"z":8.0},{"cubeType":1,"time":59.0399971,"x":-0.04,"y":9.14,"z":8.0},{"cubeType":2,"time":59.52,"x":0.04,"y":9.18,"z":8.0},{"cubeType":3,"time":60.0,"x":-0.1,"y":9.18,"z":8.0},{"cubeType":0,"time":60.48,"x":0.04,"y":9.14,"z":8.0},{"cubeType":2,"time":60.96,"x":0.1,"y":9.2,"z":8.0},{"cubeType":0,"time":61.44,"x":0.08,"y":9.14,"z":8.0},{"cubeType":1,"time":61.44,"x":-0.08,"y":9.14,"z":8.0},{"cubeType":2,"time":62.8799973,"x":0.08,"y":9.2,"z":8.0},{"cubeType":3,"time":62.8799973,"x":-0.08,"y":9.2,"z":8.0},{"cubeType":0,"time":63.3599968,"x":0.1,"y":9.14,"z":8.0},{"cubeType":1,"time":63.3599968,"x":-0.1,"y":9.14,"z":8.0},{"cubeType":3,"time":63.84,"x":-0.1,"y":9.2,"z":8.0},{"cubeType":2,"time":64.56,"x":0.04,"y":9.2,"z":8.0},{"cubeType":1,"time":65.04,"x":-0.04,"y":9.14,"z":8.0},{"cubeType":0,"time":65.76,"x":0.04,"y":9.14,"z":8.0},{"cubeType":2,"time":66.24,"x":0.1,"y":9.2,"z":8.0},{"cubeType":3,"time":66.72,"x":-0.04,"y":9.2,"z":8.0},{"cubeType":0,"time":67.2,"x":0.1,"y":9.14,"z":8.0},{"cubeType":1,"time":67.2,"x":-0.1,"y":9.14,"z":8.0},{"cubeType":3,"time":67.68,"x":-0.1,"y":9.2,"z":8.0},{"cubeType":1,"time":68.159996,"x":-0.04,"y":9.2,"z":8.0},{"cubeType":2,"time":68.64,"x":0.08,"y":9.12,"z":8.0},{"cubeType":3,"time":68.64,"x":-0.08,"y":9.12,"z":8.0}]
